chatgpt4pcg/__init__.py
chatgpt4pcg/competition.py
chatgpt4pcg/utils.py
chatgpt4pcg/models/__init__.py
chatgpt4pcg/models/trial_context.py
chatgpt4pcg/models/trial_loop.py
chatgpt4pcg-1.2.2.dist-info/LICENSE
chatgpt4pcg-1.2.2.dist-info/METADATA
chatgpt4pcg-1.2.2.dist-info/WHEEL
chatgpt4pcg-1.2.2.dist-info/top_level.txt
chatgpt4pcg-1.2.2.dist-info/RECORD
