Metadata-Version: 2.1
Name: chatgpt4pcg
Version: 1.2.2
Summary: ChatGPT4PCG is a python package containing required and utility functions as a part of ChatGPT4PCG competition.
Author-email: ChatGPT4PCG Organizing Team <chatgpt4pcg@gmail.com>, Pittawat Taveekitworachai <pittawat.pete@gmail.com>
Maintainer-email: Pittawat Taveekitworachai <pittawat.pete@gmail.com>
License: MIT License
Project-URL: Homepage, https://chatgpt4pcg.github.io/
Project-URL: Bug Reports, https://github.com/chatgpt4pcg/chatgpt4pcg-python/issues
Project-URL: Source, https://github.com/chatgpt4pcg/chatgpt4pcg-python
Keywords: chatgpt,chatgpt4pcg,competition
Classifier: Development Status :: 3 - Alpha
Classifier: Intended Audience :: Developers
Classifier: Topic :: Software Development
Classifier: License :: OSI Approved :: MIT License
Classifier: Programming Language :: Python :: 3
Classifier: Programming Language :: Python :: 3.11
Classifier: Programming Language :: Python :: 3 :: Only
Requires-Python: >=3.11
License-File: LICENSE
Requires-Dist: openai
